Bynd/__bynd__.py
Bynd/__byndref__.py
Bynd/__init__.py
Bynd/bynd.py
bynd-2.6.dist-info/METADATA
bynd-2.6.dist-info/WHEEL
bynd-2.6.dist-info/RECORD
