Metadata-Version: 2.4
Name: Bynd
Version: 2.6
Summary: Bynd is a way of introducing static typing to Python.
Author-email: "Rayshawn Levy (sneekyfoxx)" <sneekyfoxx09@gmail.com>
Maintainer-email: "Rayshawn Levy (sneekyfoxx)" <sneekyfoxx09@gmail.com>
Keywords: Bind,Bynd,bind,bynd
Classifier: Development Status :: 5 - Production/Stable
Classifier: Intended Audience :: Developers
Classifier: Natural Language :: English
Classifier: Operating System :: OS Independent
Classifier: Programming Language :: Python :: 3.10
Classifier: Programming Language :: Python :: 3.11
Classifier: Programming Language :: Python :: 3.12
Classifier: Programming Language :: Python :: 3.13
Classifier: Topic :: Other/Nonlisted Topic
Classifier: Typing :: Typed
Requires-Python: >=3.10
